sqlite3db/__init__.py
sqlite3db/api.py
sqlite3db-0.0.1.dist-info/LICENSE
sqlite3db-0.0.1.dist-info/METADATA
sqlite3db-0.0.1.dist-info/WHEEL
sqlite3db-0.0.1.dist-info/top_level.txt
sqlite3db-0.0.1.dist-info/RECORD
