Metadata-Version: 2.1
Name: sqlite3db
Version: 0.0.1
Summary: A package that manages database through sqlite3
Author: Mengke Lu
Author-email: <mklu0611@gmail.com>
Keywords: python,sqlite3
Classifier: Development Status :: 1 - Planning
Classifier: Intended Audience :: Developers
Classifier: Programming Language :: Python :: 3
Classifier: Operating System :: Unix
Classifier: Operating System :: MacOS :: MacOS X
Classifier: Operating System :: Microsoft :: Windows
Requires-Python: >=3.7
License-File: LICENSE
